reddish/__init__.py
reddish/_command.py
reddish/_errors.py
reddish/_parser.py
reddish/_sansio.py
reddish/_templating.py
reddish/_typing.py
reddish/_utils.py
reddish/models/__init__.py
reddish/models/_basic.py
reddish/socket/__init__.py
reddish/socket/_client.py
reddish/trio/__init__.py
reddish/trio/_client.py
reddish-0.4.0.dist-info/LICENSE
reddish-0.4.0.dist-info/WHEEL
reddish-0.4.0.dist-info/METADATA
reddish-0.4.0.dist-info/RECORD
