Metadata-Version: 2.1
Name: reddish
Version: 0.4.0
Summary: An async redis client library with a minimal api
Home-page: https://github.com/stereobutter/reddish
License: MIT
Keywords: redis
Author: Sascha Desch
Author-email: sascha.desch@hotmail.com
Requires-Python: >=3.7,<4.0
Classifier: License :: OSI Approved :: MIT License
Classifier: Programming Language :: Python :: 3
Classifier: Programming Language :: Python :: 3.10
Classifier: Programming Language :: Python :: 3.7
Classifier: Programming Language :: Python :: 3.8
Classifier: Programming Language :: Python :: 3.9
Provides-Extra: trio
Requires-Dist: hiredis (>=2.0.0,<3.0.0)
Requires-Dist: pydantic (>=1.8.2,<2.0.0)
Requires-Dist: trio (>=0.19.0,<0.20.0); extra == "trio"
Project-URL: Repository, https://github.com/stereobutter/reddish
